Metadata-Version: 2.1
Name: graphoW
Version: 0.4
Summary: graphoW is a Python package for the creation of a Graph-of-Words (GoW) representation of texts.
Home-page: https://github.com/tommantonela/graphoW
Author: Antonela Tommasel
Author-email: antonela.tommasel@isistan.unicen.edu.ar
License: apache-2.0
Download-URL: https://github.com/tommantonela/graphoW/archive/v_04.tar.gz
Keywords: graph-of-words,text analysis,natural language processing
Platform: UNKNOWN
Classifier: Development Status :: 3 - Alpha
Classifier: Intended Audience :: Science/Research
Classifier: Intended Audience :: Developers
Classifier: Topic :: Scientific/Engineering :: Information Analysis
Classifier: Topic :: Text Processing :: Linguistic
Classifier: License :: OSI Approved :: Apache Software License
Classifier: Natural Language :: English
Classifier: Programming Language :: Python :: 3
Classifier: Programming Language :: Python :: 3.7
